minimalist_RL/SAC.py
minimalist_RL/__init__.py
minimalist_RL/utils.py
minimalist_rl-0.0.8.dist-info/METADATA
minimalist_rl-0.0.8.dist-info/WHEEL
minimalist_rl-0.0.8.dist-info/top_level.txt
minimalist_rl-0.0.8.dist-info/RECORD
