Metadata-Version: 2.4
Name: minimalist-RL
Version: 0.0.8
Summary: Minimalist & Decoupled Reinforcement Learning.
Home-page: https://github.com/NeuroAI-Research/minimalist-RL
Author: Ricky Ding
Author-email: e0134117@u.nus.edu
License: MIT
Keywords: reinforcement-learning,rl,ppo,sac,pytorch,minimalist
Classifier: Intended Audience :: Education
Classifier: Topic :: Scientific/Engineering :: Artificial Intelligence
Classifier: License :: OSI Approved :: MIT License
Classifier: Programming Language :: Python :: 3
Classifier: Operating System :: OS Independent
Requires-Python: >=3.8
Requires-Dist: gymnasium
Requires-Dist: numpy
Requires-Dist: torch
Requires-Dist: trading_models
Dynamic: author
Dynamic: author-email
Dynamic: classifier
Dynamic: description
Dynamic: description-content-type
Dynamic: home-page
Dynamic: keywords
Dynamic: license
Dynamic: requires-dist
Dynamic: requires-python
Dynamic: summary
